setup.cfg
setup.py
AllAboutLinkedList/Algorithems.py
AllAboutLinkedList/HowToUse_internalFunctions.py
AllAboutLinkedList/HowToUse_intersection.py
AllAboutLinkedList/HowToUse_loop.py
AllAboutLinkedList/HowToUse_reverse.py
AllAboutLinkedList/HowToUse_sort.py
AllAboutLinkedList/Implementation.py
AllAboutLinkedList.egg-info/PKG-INFO
AllAboutLinkedList.egg-info/SOURCES.txt
AllAboutLinkedList.egg-info/dependency_links.txt
AllAboutLinkedList.egg-info/top_level.txt