Metadata-Version: 1.1
Name: AllAboutLinkedList
Version: 0.1
Summary: implemntation and helpful algorithems for linked lists
Home-page: https://github.com/barakbattach/LinkedList
Author: barak battac
Author-email: barakbattacn@gmail.com
License: UNKNOWN
Download-URL: https://github.com/BarakBat/LinkedList.git
Keywords: linkedlist,algorithem,testing
Platform: UNKNOWN
